{
  "crews": [{"id":1,"name":"Come Thirty"},{"id":2,"name":"Several Fastened"},{"id":3,"name":"Ate Pine"},{"id":4,"name":"Donkey Dust"},{"id":5,"name":"Climb Hunter"},{"id":6,"name":"Perhaps Tea"},{"id":7,"name":"Then Luck"},{"id":8,"name":"Tree Home"},{"id":9,"name":"Principle Wheat"},{"id":10,"name":"Crop Tightly"},{"id":11,"name":"Income Cup"},{"id":12,"name":"Happen Trip"},{"id":13,"name":"Cell Thick"},{"id":14,"name":"Compound Hundred"},{"id":15,"name":"Hardly Learn"},{"id":16,"name":"Area Meal"},{"id":17,"name":"Verb Suddenly"},{"id":18,"name":"Sat Familiar"},{"id":19,"name":"Wool Excited"},{"id":20,"name":"Trick Wash"},{"id":21,"name":"Tower Bent"},{"id":22,"name":"Spend Basis"},{"id":23,"name":"Hundred Steep"},{"id":24,"name":"Dog Depth"},{"id":25,"name":"Cotton Vertical"},{"id":26,"name":"Loud Rich"},{"id":27,"name":"Sold Younger"},{"id":28,"name":"Extra If"},{"id":29,"name":"Twice Stick"},{"id":30,"name":"Adjective Gravity"}],
  "districts": [{"id":1,"name":"Once Wrapped"},{"id":2,"name":"Silk Manufacturing"},{"id":3,"name":"Steep Simplest"},{"id":4,"name":"Classroom Mysterious"},{"id":5,"name":"Glass Breathe"},{"id":6,"name":"Adjective Activity"},{"id":7,"name":"Dress Poet"},{"id":8,"name":"System Proud"},{"id":9,"name":"Kill Divide"},{"id":10,"name":"Rocky Wagon"},{"id":11,"name":"Shout Hunter"},{"id":12,"name":"Now Habit"},{"id":13,"name":"Nails Given"},{"id":14,"name":"Clothing Colony"},{"id":15,"name":"Transportation If"},{"id":16,"name":"Cause Sister"},{"id":17,"name":"Likely Married"},{"id":18,"name":"Wolf Clock"},{"id":19,"name":"Such Chain"},{"id":20,"name":"Come Necessary"},{"id":21,"name":"Did Select"},{"id":22,"name":"Distance Ants"},{"id":23,"name":"Production Doll"},{"id":24,"name":"Gain Might"},{"id":25,"name":"Room Vegetable"},{"id":26,"name":"Slabs Becoming"},{"id":27,"name":"Seldom Standard"},{"id":28,"name":"Job Return"},{"id":29,"name":"Sand Wave"},{"id":30,"name":"Monkey Again"}],
  "locations": [{"id":1,"name":"Environment Means"},{"id":2,"name":"Practice Tape"},{"id":3,"name":"Past Sentence"},{"id":4,"name":"Herself Level"},{"id":5,"name":"Rise Shelf"},{"id":6,"name":"Mice Ear"},{"id":7,"name":"Slide Sort"},{"id":8,"name":"Rose Fort"},{"id":9,"name":"Greatly Stomach"},{"id":10,"name":"Too Daily"},{"id":11,"name":"Pain Rough"},{"id":12,"name":"Seen Mouse"},{"id":13,"name":"Road Period"},{"id":14,"name":"Goes Reason"},{"id":15,"name":"Faster Whispered"},{"id":16,"name":"Building Children"},{"id":17,"name":"Dot Pool"},{"id":18,"name":"With Became"},{"id":19,"name":"Apart Page"},{"id":20,"name":"Height Natural"},{"id":21,"name":"But Interior"},{"id":22,"name":"Top Cross"},{"id":23,"name":"Noon Grass"},{"id":24,"name":"Southern Related"},{"id":25,"name":"Structure Floating"},{"id":26,"name":"Cry Notice"},{"id":27,"name":"Surrounded Game"},{"id":28,"name":"Fifteen By"},{"id":29,"name":"Nodded Zipper"},{"id":30,"name":"Till Pressure"}],
  "projects": [{"id":1,"name":"Variety Mathematics"},{"id":2,"name":"Driving Coach"},{"id":3,"name":"Count Feathers"},{"id":4,"name":"Write Clothes"},{"id":5,"name":"Grandfather Chemical"},{"id":6,"name":"Behavior Surface"},{"id":7,"name":"Separate Gently"},{"id":8,"name":"Process Buy"},{"id":9,"name":"Position Silk"},{"id":10,"name":"Not Equally"},{"id":11,"name":"Verb Provide"},{"id":12,"name":"Worker Hung"},{"id":13,"name":"Surface Conversation"},{"id":14,"name":"Support Pie"},{"id":15,"name":"Read Engineer"},{"id":16,"name":"Ran Drop"},{"id":17,"name":"Saw Paper"},{"id":18,"name":"Still Addition"},{"id":19,"name":"Met Waste"},{"id":20,"name":"Throat Away"},{"id":21,"name":"Finest Difference"},{"id":22,"name":"Tape Jump"},{"id":23,"name":"Noun Warm"},{"id":24,"name":"Material Left"},{"id":25,"name":"Pain Right"},{"id":26,"name":"Gravity Rubber"},{"id":27,"name":"Offer Hungry"},{"id":28,"name":"Unless Compass"},{"id":29,"name":"Plural Useful"},{"id":30,"name":"Offer Applied"}],
  "profile": {
    "name": "typicode"
  }
}
